cardano_gasless_tx/__init__.py
cardano_gasless_tx/main.py
cardano_gasless_tx/util.py
cardano_gasless_tx/wallet.py
cardano_gasless_tx-1.0.3.dist-info/LICENSE
cardano_gasless_tx-1.0.3.dist-info/METADATA
cardano_gasless_tx-1.0.3.dist-info/WHEEL
cardano_gasless_tx-1.0.3.dist-info/top_level.txt
cardano_gasless_tx-1.0.3.dist-info/RECORD
