Metadata-Version: 2.2
Name: cardano-gasless-tx
Version: 1.0.3
Summary: Gasless Tx Library for Cardano
Author-email: Nucast <contact@nucast.io>
License: MIT
Project-URL: Homepage, https://github.com/Nucastio/gasless-python-lib
Project-URL: Issues, https://github.com/Nucastio/gasless-python-lib/issues
Requires-Python: >=3.8
License-File: LICENSE
Requires-Dist: requests>=2.31.0
Requires-Dist: pycardano>=0.13.0
Requires-Dist: fastapi>=0.111.1
Requires-Dist: bip-utils>=2.9.3
Requires-Dist: cbor2>=5.6.5
Requires-Dist: blockfrost-python>=0.6.0
Requires-Dist: uvicorn>=0.30.3
